Metadata-Version: 2.0
Name: irco
Version: 0.10.2
Summary: International Research Collaboration Graphs
Home-page: https://github.com/GaretJax/irco
Author: Jonathan Stoppani
Author-email: jonathan@stoppani.name
License: MIT
Platform: UNKNOWN
Classifier: Development Status :: 4 - Beta
Classifier: Intended Audience :: Developers
Classifier: License :: OSI Approved :: MIT License
Classifier: Operating System :: OS Independent
Classifier: Programming Language :: Python
Classifier: Topic :: Software Development :: Libraries :: Python Modules
Requires-Dist: Flask (==0.10.1)
Requires-Dist: Jinja2 (==2.7.1)
Requires-Dist: Mako (==1.0.0)
Requires-Dist: MarkupSafe (==0.18)
Requires-Dist: SQLAlchemy (==0.9.3)
Requires-Dist: Werkzeug (==0.9.4)
Requires-Dist: ftfy (==3.0.4)
Requires-Dist: itsdangerous (==0.23)
Requires-Dist: networkx (==1.7)
Requires-Dist: pycountry (==0.19)
Requires-Dist: requests (==1.2.3)
Requires-Dist: structlog (==0.3.2)
Requires-Dist: tablib-garetjax (==0.9.12)
Requires-Dist: raven (==4.2.1)
Requires-Dist: alembic (==0.6.6)
